wise_print/__init__.py
wise_print/custom_printer.py
wise_print-0.1.6.dist-info/LICENSE
wise_print-0.1.6.dist-info/METADATA
wise_print-0.1.6.dist-info/WHEEL
wise_print-0.1.6.dist-info/top_level.txt
wise_print-0.1.6.dist-info/RECORD
