Metadata-Version: 2.1
Name: wise_print
Version: 0.1.6
Summary: Simple package to add info to print statements
Home-page: https://github.com/dandpz/wise-print
Author: Daniele Dapuzzo
Author-email: 
Project-URL: Documentation, https://github.com/dandpz/wise-print
Project-URL: Bug Reports, https://github.com/dandpz/wise-print/issues
Project-URL: Source Code, https://github.com/dandpz/wise-print
Keywords: print,pypi,package,logging
Classifier: Development Status :: 4 - Beta
Classifier: Intended Audience :: Developers
Classifier: Topic :: Software Development :: Libraries
Classifier: Topic :: Software Development :: Debuggers
Classifier: Programming Language :: Python :: 3.9
Classifier: Programming Language :: Python :: 3.10
Classifier: Programming Language :: Python :: 3.11
Classifier: Programming Language :: Python :: 3 :: Only
Classifier: License :: OSI Approved :: MIT License
Classifier: Operating System :: OS Independent
Requires-Python: >=3.9
License-File: LICENSE
Provides-Extra: dev
Requires-Dist: check-manifest; extra == "dev"
